{"start_time":1506584954000,"end_time":1506593805000,"created_at":1506623904000,"updated_at":1506623916000,"start_time_timezone_offset":10800000,"end_time_timezone_offset":10800000,"distance":21095,"duration":8849649,"elevation_gain":9,"elevation_loss":7,"average_speed":8.58145809173584,"calories":1857,"longitude":30.5537643432617,"latitude":50.7579383850098,"max_speed":14.2450389862061,"pause_duration":1351,"duration_per_km":419514,"temperature":12.0,"pulse_avg":155,"pulse_max":185,"max_step_frequency":176,"avg_step_frequency":157,"total_steps":23440,"manual":false,"edited":false,"completed":true,"live_tracking_active":false,"live_tracking_enabled":false,"cheering_enabled":false,"indoor":false,"id":"1887a928-fcd3-4429-b3e4-60bfa4fff24d","weather_condition_id":"1","sport_type_id":"1"}