[{"type":"sleep_phase_transition","stage":"awake","timestamp":1477258721000},{"type":"sleep_phase_transition","stage":"light_sleep","timestamp":1477258901000},{"type":"sleep_phase_transition","stage":"awake","timestamp":1477273661000},{"type":"sleep_phase_transition","stage":"deep_sleep","timestamp":1477273781000},{"type":"sleep_phase_transition","stage":"light_sleep","timestamp":1477273841000},{"type":"sleep_phase_transition","stage":"deep_sleep","timestamp":1477273901000},{"type":"sleep_phase_transition","stage":"awake","timestamp":1477274621000},{"type":"sleep_phase_transition","stage":"deep_sleep","timestamp":1477274681000},{"type":"sleep_phase_transition","stage":"light_sleep","timestamp":1477274741000},{"type":"sleep_phase_transition","stage":"deep_sleep","timestamp":1477274801000},{"type":"sleep_phase_transition","stage":"light_sleep","timestamp":1477276601000},{"type":"sleep_phase_transition","stage":"deep_sleep","timestamp":1477276661000},{"type":"sleep_phase_transition","stage":"light_sleep","timestamp":1477277021000},{"type":"sleep_phase_transition","stage":"deep_sleep","timestamp":1477277381000},{"type":"sleep_phase_transition","stage":"light_sleep","timestamp":1477278341000},{"type":"sleep_phase_transition","stage":"deep_sleep","timestamp":1477278401000},{"type":"sleep_phase_transition","stage":"light_sleep","timestamp":1477278701000},{"type":"sleep_phase_transition","stage":"deep_sleep","timestamp":1477278761000},{"type":"sleep_phase_transition","stage":"awake","timestamp":1477278881000},{"type":"sleep_phase_transition","stage":"deep_sleep","timestamp":1477278941000},{"type":"sleep_phase_transition","stage":"light_sleep","timestamp":1477279061000},{"type":"sleep_phase_transition","stage":"deep_sleep","timestamp":1477279121000},{"type":"sleep_phase_transition","stage":"light_sleep","timestamp":1477279421000},{"type":"sleep_phase_transition","stage":"deep_sleep","timestamp":1477279601000},{"type":"sleep_phase_transition","stage":"light_sleep","timestamp":1477280621000},{"type":"sleep_phase_transition","stage":"deep_sleep","timestamp":1477280921000},{"type":"sleep_phase_transition","stage":"awake","timestamp":1477281041000},{"type":"sleep_phase_transition","stage":"deep_sleep","timestamp":1477281101000},{"type":"sleep_phase_transition","stage":"light_sleep","timestamp":1477281761000},{"type":"sleep_phase_transition","stage":"deep_sleep","timestamp":1477281821000},{"type":"sleep_phase_transition","stage":"light_sleep","timestamp":1477283141000},{"type":"sleep_phase_transition","stage":"deep_sleep","timestamp":1477283201000},{"type":"sleep_phase_transition","stage":"awake","timestamp":1477283321000},{"type":"sleep_phase_transition","stage":"light_sleep","timestamp":1477283561000},{"type":"sleep_phase_transition","stage":"deep_sleep","timestamp":1477283681000},{"type":"sleep_phase_transition","stage":"awake","timestamp":1477283741000},{"type":"sleep_phase_transition","stage":"light_sleep","timestamp":1477285961000},{"type":"sleep_phase_transition","stage":"deep_sleep","timestamp":1477286021000},{"type":"sleep_phase_transition","stage":"light_sleep","timestamp":1477286501000},{"type":"sleep_phase_transition","stage":"deep_sleep","timestamp":1477286561000},{"type":"sleep_phase_transition","stage":"light_sleep","timestamp":1477287821000},{"type":"sleep_phase_transition","stage":"deep_sleep","timestamp":1477288001000},{"type":"sleep_phase_transition","stage":"light_sleep","timestamp":1477288961000},{"type":"sleep_phase_transition","stage":"deep_sleep","timestamp":1477289021000},{"type":"sleep_phase_transition","stage":"light_sleep","timestamp":1477290581000},{"type":"sleep_phase_transition","stage":"deep_sleep","timestamp":1477290941000},{"type":"sleep_phase_transition","stage":"light_sleep","timestamp":1477292021000},{"type":"sleep_phase_transition","stage":"deep_sleep","timestamp":1477292081000},{"type":"sleep_phase_transition","stage":"awake","timestamp":1477293161000},{"type":"sleep_phase_transition","stage":"light_sleep","timestamp":1477293221000},{"type":"sleep_phase_transition","stage":"deep_sleep","timestamp":1477293281000},{"type":"sleep_phase_transition","stage":"light_sleep","timestamp":1477293521000},{"type":"sleep_phase_transition","stage":"deep_sleep","timestamp":1477293581000},{"type":"sleep_phase_transition","stage":"light_sleep","timestamp":1477294061000},{"type":"sleep_phase_transition","stage":"deep_sleep","timestamp":1477294121000},{"type":"sleep_phase_transition","stage":"awake","timestamp":1477294841000},{"type":"sleep_phase_transition","stage":"light_sleep","timestamp":1477294901000},{"type":"sleep_phase_transition","stage":"awake","timestamp":1477294961000}]