[{"version":1,"timestamp":1512343800000,"precision":15,"offset":0,"value":14},
{"version":1,"timestamp":1512343800000,"precision":15,"offset":435,"value":24},
{"version":1,"timestamp":1512343800000,"precision":15,"offset":450,"value":139},
{"version":1,"timestamp":1512343800000,"precision":15,"offset":465,"value":107},
{"version":1,"timestamp":1512343800000,"precision":15,"offset":480,"value":223},
{"version":1,"timestamp":1512343800000,"precision":15,"offset":495,"value":20},
{"version":1,"timestamp":1512343800000,"precision":15,"offset":510,"value":125},
{"version":1,"timestamp":1512343800000,"precision":15,"offset":525,"value":70},
{"version":1,"timestamp":1512343800000,"precision":15,"offset":570,"value":22},
{"version":1,"timestamp":1512343800000,"precision":15,"offset":585,"value":182},
{"version":1,"timestamp":1512343800000,"precision":15,"offset":675,"value":70},
{"version":1,"timestamp":1512343800000,"precision":15,"offset":855,"value":33},
{"version":1,"timestamp":1512343800000,"precision":15,"offset":870,"value":2239},
{"version":1,"timestamp":1512343800000,"precision":15,"offset":885,"value":2506},
{"version":1,"timestamp":1512343800000,"precision":15,"offset":900,"value":1807},
{"version":1,"timestamp":1512343800000,"precision":15,"offset":915,"value":72}]